docs/source/conf.py
examples/evaluation/agent.py
examples/evaluation/create_project.py
examples/evaluation/evaluate.py
mixedvoices/__init__.py
mixedvoices/cli.py
mixedvoices/config.py
mixedvoices/constants.py
mixedvoices/models.py
mixedvoices/utils.py
mixedvoices/core/__init__.py
mixedvoices/core/project.py
mixedvoices/core/recording.py
mixedvoices/core/step.py
mixedvoices/core/task_manager.py
mixedvoices/core/utils.py
mixedvoices/core/version.py
mixedvoices/dashboard/__init__.py
mixedvoices/dashboard/app.py
mixedvoices/dashboard/cli.py
mixedvoices/dashboard/config.py
mixedvoices/dashboard/utils.py
mixedvoices/dashboard/api/__init__.py
mixedvoices/dashboard/api/client.py
mixedvoices/dashboard/api/endpoints.py
mixedvoices/dashboard/components/__init__.py
mixedvoices/dashboard/components/evaluator_viewer.py
mixedvoices/dashboard/components/metrics_manager.py
mixedvoices/dashboard/components/project_creator.py
mixedvoices/dashboard/components/recording_viewer.py
mixedvoices/dashboard/components/sidebar.py
mixedvoices/dashboard/components/success_criteria_manager.py
mixedvoices/dashboard/components/upload_form.py
mixedvoices/dashboard/components/version_creator.py
mixedvoices/dashboard/components/version_selector.py
mixedvoices/dashboard/content/logo.png
mixedvoices/dashboard/pages/0_versions.py
mixedvoices/dashboard/pages/10_create_evaluator_create_prompts.py
mixedvoices/dashboard/pages/1_metrics.py
mixedvoices/dashboard/pages/1_success_criteria.py
mixedvoices/dashboard/pages/2_view_flow.py
mixedvoices/dashboard/pages/3_view_recordings.py
mixedvoices/dashboard/pages/4_upload_recording.py
mixedvoices/dashboard/pages/5_evals_list.py
mixedvoices/dashboard/pages/6_eval_details.py
mixedvoices/dashboard/pages/7_eval_run_details.py
mixedvoices/dashboard/pages/8_create_evaluator_agent_prompt.py
mixedvoices/dashboard/pages/9_create_evaluator_select_metrics.py
mixedvoices/dashboard/visualizations/__init__.py
mixedvoices/dashboard/visualizations/flow_chart.py
mixedvoices-1.0.2.dist-info/LICENSE
mixedvoices-1.0.2.dist-info/METADATA
mixedvoices-1.0.2.dist-info/WHEEL
mixedvoices-1.0.2.dist-info/entry_points.txt
mixedvoices-1.0.2.dist-info/top_level.txt
mixedvoices-1.0.2.dist-info/RECORD
