Metadata-Version: 2.1
Name: mixedvoices
Version: 1.0.2
Summary: Analytics and Evaluation Tool for Voice Agents
Author-email: Abhinav <abhinav@mixedvoices.xyz>
License: Apache-2.0
Project-URL: Homepage, https://github.com/MixedVoices/MixedVoices
Project-URL: Repository, https://github.com/MixedVoices/MixedVoices.git
Project-URL: Documentation, https://github.com/MixedVoices/MixedVoices#readme
Classifier: Development Status :: 3 - Alpha
Classifier: Intended Audience :: Developers
Classifier: Programming Language :: Python :: 3.8
Classifier: Programming Language :: Python :: 3.9
Classifier: Programming Language :: Python :: 3.10
Classifier: Programming Language :: Python :: 3.11
Classifier: License :: OSI Approved :: Apache Software License
Classifier: Topic :: Software Development :: Libraries :: Python Modules
Classifier: Topic :: Software Development :: Testing
Classifier: Topic :: Scientific/Engineering :: Artificial Intelligence
Requires-Python: >=3.8
License-File: LICENSE
Requires-Dist: pydantic>=2.5.0
Requires-Dist: openai>=1.51.0
Requires-Dist: librosa>=0.10.0
Requires-Dist: typer>=0.9.0
Requires-Dist: fastapi>=0.100.0
Requires-Dist: uvicorn>=0.22.0
Requires-Dist: python-multipart>=0.0.6
Requires-Dist: streamlit>=1.40.0
Requires-Dist: plotly>=5.13.1
Requires-Dist: streamlit-plotly-events>=0.0.6
Requires-Dist: networkx>=3.0
Requires-Dist: aiohttp>=3.8.4
Provides-Extra: dev
Requires-Dist: black>=23.12.0; extra == "dev"
Requires-Dist: ruff>=0.1.9; extra == "dev"
Requires-Dist: pytest>=7.5.2; extra == "dev"
Requires-Dist: pytest-asyncio>=0.21.0; extra == "dev"
Requires-Dist: httpx>=0.25.3; extra == "dev"
Requires-Dist: pytest-cov>=4.1.0; extra == "dev"
Requires-Dist: sphinx; extra == "dev"
Requires-Dist: sphinx-rtd-theme; extra == "dev"
Requires-Dist: sphinxcontrib-napoleon; extra == "dev"
